lasuite/plugins/kyutai/__init__.py
lasuite/plugins/kyutai/log.py
lasuite/plugins/kyutai/py.typed
lasuite/plugins/kyutai/stt.py
lasuite/plugins/kyutai/version.py
livekit_plugins_kyutai_lasuite-0.0.6.dist-info/METADATA
livekit_plugins_kyutai_lasuite-0.0.6.dist-info/WHEEL
livekit_plugins_kyutai_lasuite-0.0.6.dist-info/RECORD
